pkgmgr/__init__.py
pkgmgr/_version.py
pkgmgr/aio.py
pkgmgr/cli.py
pkgmgr/command.py
pkgmgr/core.py
pkgmgr/helpers.py
pkgmgr/printer.py
pkgmgr/registry.py
pkgmgr-1.1.0.dist-info/licenses/LICENSE
pkgmgr-1.1.0.dist-info/METADATA
pkgmgr-1.1.0.dist-info/WHEEL
pkgmgr-1.1.0.dist-info/entry_points.txt
pkgmgr-1.1.0.dist-info/top_level.txt
pkgmgr-1.1.0.dist-info/RECORD
