Metadata-Version: 2.4
Name: pkgmgr
Version: 1.1.0
Summary: Extensible package and configuration manager
Author: soraxas
License: MIT License
Requires-Python: >=3.10
License-File: LICENSE
Requires-Dist: typer==0.15.4
Provides-Extra: dev
Requires-Dist: build; extra == "dev"
Requires-Dist: dapperdata; extra == "dev"
Requires-Dist: mypy; extra == "dev"
Requires-Dist: pytest; extra == "dev"
Requires-Dist: pytest-asyncio; extra == "dev"
Requires-Dist: pytest-cov; extra == "dev"
Requires-Dist: pytest-pretty; extra == "dev"
Requires-Dist: ruamel.yaml; extra == "dev"
Requires-Dist: ruff; extra == "dev"
Requires-Dist: toml-sort; extra == "dev"
Dynamic: license-file
